{
  "card_id": "EB02-050",
  "card_number": "EB02-050",
  "name": "Kokoro no Chizu",
  "history": [
    {
      "date": "2026-06-22",
      "market_price": 0.91,
      "low_price": null
    },
    {
      "date": "2026-06-26",
      "market_price": 1,
      "low_price": null
    },
    {
      "date": "2026-06-30",
      "market_price": 0.84,
      "low_price": null
    },
    {
      "date": "2026-07-02",
      "market_price": 0.8496,
      "low_price": null
    },
    {
      "date": "2026-07-04",
      "market_price": 0.85,
      "low_price": null
    },
    {
      "date": "2026-07-08",
      "market_price": 0.85,
      "low_price": null
    },
    {
      "date": "2026-07-10",
      "market_price": 0.85,
      "low_price": null
    },
    {
      "date": "2026-07-12",
      "market_price": 0.82,
      "low_price": null
    },
    {
      "date": "2026-07-14",
      "market_price": 0.81,
      "low_price": null
    }
  ]
}