{
  "card_id": "OP06-066_p3",
  "card_number": "OP06-066",
  "name": "Vinsmoke Yonji",
  "history": [
    {
      "date": "2026-06-22",
      "market_price": 5.15,
      "low_price": null
    },
    {
      "date": "2026-06-26",
      "market_price": 5.09,
      "low_price": null
    },
    {
      "date": "2026-06-30",
      "market_price": 5.03,
      "low_price": null
    },
    {
      "date": "2026-07-02",
      "market_price": 5.03,
      "low_price": null
    },
    {
      "date": "2026-07-04",
      "market_price": 5.02,
      "low_price": null
    },
    {
      "date": "2026-07-08",
      "market_price": 4.96,
      "low_price": null
    },
    {
      "date": "2026-07-10",
      "market_price": 4.96,
      "low_price": null
    },
    {
      "date": "2026-07-12",
      "market_price": 4.96,
      "low_price": null
    },
    {
      "date": "2026-07-14",
      "market_price": 4.96,
      "low_price": null
    },
    {
      "date": "2026-07-16",
      "market_price": 4.96,
      "low_price": null
    }
  ]
}