{
  "card_id": "OP07-001_p2",
  "card_number": "OP07-001",
  "name": "Monkey.D.Dragon",
  "history": [
    {
      "date": "2026-06-26",
      "market_price": 21.3,
      "low_price": null
    },
    {
      "date": "2026-06-30",
      "market_price": 21.54,
      "low_price": null
    },
    {
      "date": "2026-07-02",
      "market_price": 21.71,
      "low_price": null
    },
    {
      "date": "2026-07-04",
      "market_price": 21.88,
      "low_price": null
    },
    {
      "date": "2026-07-08",
      "market_price": 21.93,
      "low_price": null
    }
  ]
}