{
  "card_id": "OP12-029",
  "card_number": "OP12-029",
  "name": "Shimotsuki Kouzaburou",
  "history": [
    {
      "date": "2026-06-22",
      "market_price": 6.06,
      "low_price": null
    },
    {
      "date": "2026-06-26",
      "market_price": 6.06,
      "low_price": null
    },
    {
      "date": "2026-06-30",
      "market_price": 6.11,
      "low_price": null
    },
    {
      "date": "2026-07-02",
      "market_price": 6.11,
      "low_price": null
    },
    {
      "date": "2026-07-04",
      "market_price": 6.11,
      "low_price": null
    },
    {
      "date": "2026-07-08",
      "market_price": 5.84,
      "low_price": null
    },
    {
      "date": "2026-07-10",
      "market_price": 5.84,
      "low_price": null
    }
  ]
}