{
  "card_id": "OP13-103",
  "card_number": "OP13-103",
  "name": "Gyogyo",
  "history": [
    {
      "date": "2026-06-22",
      "market_price": 0.23,
      "low_price": null
    },
    {
      "date": "2026-06-26",
      "market_price": 0.24,
      "low_price": null
    },
    {
      "date": "2026-06-30",
      "market_price": 0.24,
      "low_price": null
    },
    {
      "date": "2026-07-02",
      "market_price": 0.23,
      "low_price": null
    },
    {
      "date": "2026-07-04",
      "market_price": 0.24,
      "low_price": null
    },
    {
      "date": "2026-07-08",
      "market_price": 0.24,
      "low_price": null
    },
    {
      "date": "2026-07-10",
      "market_price": 0.25,
      "low_price": null
    },
    {
      "date": "2026-07-12",
      "market_price": 0.25,
      "low_price": null
    },
    {
      "date": "2026-07-14",
      "market_price": 0.25,
      "low_price": null
    },
    {
      "date": "2026-07-16",
      "market_price": 0.25,
      "low_price": null
    },
    {
      "date": "2026-07-18",
      "market_price": 0.26,
      "low_price": null
    },
    {
      "date": "2026-07-20",
      "market_price": 0.27,
      "low_price": null
    },
    {
      "date": "2026-07-22",
      "market_price": 0.27,
      "low_price": null
    }
  ]
}